[
  {
    "title": "Why Space Is Completely Silent",
    "segments": [
      {
        "text": "In space, no one could ever hear you scream.",
        "keywords": "astronaut space"
      },
      {
        "text": "And it's not science fiction, it's pure physics.",
        "keywords": "galaxy stars space"
      },
      {
        "text": "Sound needs air or water to travel through.",
        "keywords": "speaker sound vibration"
      },
      {
        "text": "But space is an almost perfect vacuum, with nothing to carry it.",
        "keywords": "deep space nebula"
      },
      {
        "text": "So even a massive explosion out there is totally silent.",
        "keywords": "nebula explosion space"
      },
      {
        "text": "That's why in space, no one could ever hear you scream.",
        "keywords": "astronaut floating space"
      },
      {
        "text": "Follow Curio for your daily dose of science.",
        "keywords": "galaxy stars space"
      }
    ],
    "description": "A vacuum has nothing to carry sound, so space is perfectly silent. Follow for daily science & tech! 🌌",
    "hashtags": [
      "#science",
      "#space",
      "#physics",
      "#didyouknow",
      "#facts",
      "#astronomy",
      "#shorts",
      "#fyp"
    ]
  },
  {
    "title": "Your Phone Beats NASA's Moon Computer",
    "segments": [
      {
        "text": "The phone in your pocket would crush the computer that landed on the Moon.",
        "keywords": "smartphone hand"
      },
      {
        "text": "And the gap is almost impossible to imagine.",
        "keywords": "circuit board macro"
      },
      {
        "text": "The Apollo computer had about sixty four kilobytes of memory.",
        "keywords": "vintage computer"
      },
      {
        "text": "Your phone has billions of times more processing power.",
        "keywords": "smartphone screen glow"
      },
      {
        "text": "We literally walk around with supercomputers in our pockets.",
        "keywords": "person phone city"
      },
      {
        "text": "Yet that tiny computer still guided humans a quarter million miles away.",
        "keywords": "moon surface"
      },
      {
        "text": "Follow Curio for your daily dose of science.",
        "keywords": "galaxy stars space"
      }
    ],
    "description": "The Apollo computer ran on kilobytes, yet it guided humans to the Moon. Follow for daily science & tech! 🚀",
    "hashtags": [
      "#science",
      "#tech",
      "#space",
      "#nasa",
      "#didyouknow",
      "#facts",
      "#shorts",
      "#fyp"
    ]
  },
  {
    "title": "Why Lightning Is Hotter Than the Sun",
    "segments": [
      {
        "text": "A bolt of lightning is five times hotter than the surface of the Sun.",
        "keywords": "lightning storm night"
      },
      {
        "text": "And it happens in a flash too fast to see.",
        "keywords": "lightning sky"
      },
      {
        "text": "Lightning can heat the air to about thirty thousand degrees Celsius.",
        "keywords": "lightning strike"
      },
      {
        "text": "The Sun's surface is only around five thousand five hundred.",
        "keywords": "sun closeup"
      },
      {
        "text": "That sudden heat makes the air explode outward as thunder.",
        "keywords": "storm clouds dark"
      },
      {
        "text": "So every bolt is five times hotter than the Sun, in a heartbeat.",
        "keywords": "lightning night"
      },
      {
        "text": "Follow Curio for your daily dose of science.",
        "keywords": "galaxy stars space"
      }
    ],
    "description": "Lightning superheats the air to around 30,000°C, five times the Sun's surface. Follow for daily science & tech! ⚡",
    "hashtags": [
      "#science",
      "#weather",
      "#physics",
      "#lightning",
      "#didyouknow",
      "#facts",
      "#shorts",
      "#fyp"
    ]
  },
  {
    "title": "Why You Can't Remember Being a Baby",
    "segments": [
      {
        "text": "You spent years as a baby, but can't recall a single moment.",
        "keywords": "baby hands"
      },
      {
        "text": "And scientists actually have a name for it.",
        "keywords": "brain scan animation"
      },
      {
        "text": "It's called infantile amnesia.",
        "keywords": "sleeping baby"
      },
      {
        "text": "Your brain's memory system is still wiring itself in those first years.",
        "keywords": "neurons animation"
      },
      {
        "text": "You were learning constantly, but not yet storing lasting memories.",
        "keywords": "toddler playing"
      },
      {
        "text": "So your earliest years were real, your brain just never saved them.",
        "keywords": "baby smiling"
      },
      {
        "text": "Follow Curio for your daily dose of science.",
        "keywords": "galaxy stars space"
      }
    ],
    "description": "Infantile amnesia: your memory system isn't built yet to store those first years. Follow for daily science & tech! 🧠",
    "hashtags": [
      "#science",
      "#brain",
      "#psychology",
      "#memory",
      "#didyouknow",
      "#facts",
      "#shorts",
      "#fyp"
    ]
  },
  {
    "title": "Why Time Runs Faster On a Mountain",
    "segments": [
      {
        "text": "Time literally runs faster on a mountain than at the beach.",
        "keywords": "mountain peak sunrise"
      },
      {
        "text": "And it's not a trick, it's Einstein.",
        "keywords": "clock macro"
      },
      {
        "text": "Gravity actually slows down time, just a tiny bit.",
        "keywords": "planet earth space"
      },
      {
        "text": "The farther you are from Earth's mass, the faster your clock ticks.",
        "keywords": "mountain landscape"
      },
      {
        "text": "GPS satellites have to correct for this every single day.",
        "keywords": "satellite orbit earth"
      },
      {
        "text": "So someone on a mountain really does age a sliver faster than you.",
        "keywords": "mountain peak clouds"
      },
      {
        "text": "Follow Curio for your daily dose of science.",
        "keywords": "galaxy stars space"
      }
    ],
    "description": "Gravity slows time, so clocks tick faster higher up, and GPS has to correct for it. Follow for daily science & tech!",
    "hashtags": [
      "#science",
      "#physics",
      "#space",
      "#einstein",
      "#didyouknow",
      "#facts",
      "#shorts",
      "#fyp"
    ]
  }
]