{
  "title": "Why The Ocean Is A Giant Natural Battery",
  "segments": [
    {
      "text": "The ocean stores enough energy to power the world!",
      "keywords": "ocean waves energy"
    },
    {
      "text": "This is due to the movement of tides and currents.",
      "keywords": "tide waves animation"
    },
    {
      "text": "Every wave is a potential energy source.",
      "keywords": "crashing waves macro"
    },
    {
      "text": "Harnessing this energy could be game-changing.",
      "keywords": "wave energy technology"
    },
    {
      "text": "Just a fraction of it is utilized today.",
      "keywords": "untapped energy animation"
    },
    {
      "text": "Imagine the future of ocean energy production!",
      "keywords": "future energy visuals"
    },
    {
      "text": "It could power cities and reduce carbon footprints.",
      "keywords": "city skyline renewable energy"
    },
    {
      "text": "Follow Curio for your daily dose of science.",
      "keywords": "ocean energy innovation"
    }
  ],
  "description": "The ocean has untapped energy potential! Follow for daily science & tech! 🌊",
  "hashtags": [
    "#science",
    "#ocean",
    "#energy",
    "#didyouknow",
    "#facts",
    "#tech",
    "#shorts",
    "#fyp"
  ]
}